hznp_utils/__init__.py
hznp_utils/helper_functions/__init__.py
hznp_utils/helper_functions/gcp.py
hznp_utils/helper_functions/komodo.py
hznp_utils/logging.py
hznp_utils/query.py
hznp_utils/sftp.py
hznp_utils/test_helper_functions.ipynb
hznp_utils/veeva.py
hznp_utils-0.3.0.dist-info/METADATA
hznp_utils-0.3.0.dist-info/WHEEL
hznp_utils-0.3.0.dist-info/RECORD
