Metadata-Version: 2.1
Name: hznp_utils
Version: 0.3.0
Summary: Data Science utilities for Horizon Therapeutics
Author: Edwin Z.
Author-email: ezamudio@amgen.com
Requires-Python: >=3.10,<4.0
Classifier: Programming Language :: Python :: 3
Classifier: Programming Language :: Python :: 3.10
Classifier: Programming Language :: Python :: 3.11
Classifier: Programming Language :: Python :: 3.12
Requires-Dist: google-cloud-secret-manager (>=2.17.0,<3.0.0)
